tfjs_graph_converter/__init__.py
tfjs_graph_converter/api.py
tfjs_graph_converter/common.py
tfjs_graph_converter/compat.py
tfjs_graph_converter/convert_fused_depthwise.py
tfjs_graph_converter/convert_prelu.py
tfjs_graph_converter/converter.py
tfjs_graph_converter/graph_rewrite_util.py
tfjs_graph_converter/optimization.py
tfjs_graph_converter/quirks.py
tfjs_graph_converter/util.py
tfjs_graph_converter/version.py
tfjs_graph_converter-1.6.3.dist-info/LICENSE
tfjs_graph_converter-1.6.3.dist-info/METADATA
tfjs_graph_converter-1.6.3.dist-info/WHEEL
tfjs_graph_converter-1.6.3.dist-info/entry_points.txt
tfjs_graph_converter-1.6.3.dist-info/top_level.txt
tfjs_graph_converter-1.6.3.dist-info/RECORD
