Metadata-Version: 2.1
Name: tfjs-graph-converter
Version: 1.6.3
Summary: A tensorflowjs Graph Model Converter
Author-email: Patrick Levin <vertical-pink@protonmail.com>
License: MIT License
Project-URL: homepage, https://github.com/patlevin/tfjs-to-tf/
Project-URL: repository, https://github.com/patlevin/tfjs-to-tf/
Project-URL: documentation, https://github.com/patlevin/tfjs-to-tf/blob/master/docs/modules.rst
Keywords: tensorflow,tensorflowjs,converter
Classifier: Development Status :: 5 - Production/Stable
Classifier: Intended Audience :: Developers
Classifier: Intended Audience :: Education
Classifier: Intended Audience :: Science/Research
Classifier: License :: OSI Approved :: MIT License
Classifier: Programming Language :: Python :: 3
Classifier: Operating System :: OS Independent
Classifier: Topic :: Scientific/Engineering :: Artificial Intelligence
Classifier: Topic :: Software Development
Classifier: Topic :: Software Development :: Libraries
Classifier: Topic :: Software Development :: Libraries :: Python Modules
Requires-Python: >=3.6
License-File: LICENSE
Requires-Dist: tensorflowjs (>=1.5.2)
Requires-Dist: tensorflow-metal (>=2.3) ; platform_machine == "arm64"
Requires-Dist: tensorflow-macos (>=2.3) ; platform_system == "Darwin"
Provides-Extra: test
Requires-Dist: Pillow (>=8.0.0) ; extra == 'test'
